draymed/__init__.py
draymed/codes/__init__.py
draymed/codes/code_map_transform.py
draymed/codes/map.py
draymed/data/do_not_edit.txt
draymed/data/master_codes.json
draymed/pregnancy.py
draymed/py.typed
draymed-2.1.9.dist-info/WHEEL
draymed-2.1.9.dist-info/METADATA
draymed-2.1.9.dist-info/RECORD
